airflow/providers/apache/hive/__init__.py
airflow/providers/apache/hive/get_provider_info.py
airflow/providers/apache/hive/version_compat.py
airflow/providers/apache/hive/hooks/__init__.py
airflow/providers/apache/hive/hooks/hive.py
airflow/providers/apache/hive/macros/__init__.py
airflow/providers/apache/hive/macros/hive.py
airflow/providers/apache/hive/operators/__init__.py
airflow/providers/apache/hive/operators/hive.py
airflow/providers/apache/hive/operators/hive_stats.py
airflow/providers/apache/hive/plugins/__init__.py
airflow/providers/apache/hive/plugins/hive.py
airflow/providers/apache/hive/sensors/__init__.py
airflow/providers/apache/hive/sensors/hive_partition.py
airflow/providers/apache/hive/sensors/metastore_partition.py
airflow/providers/apache/hive/sensors/named_hive_partition.py
airflow/providers/apache/hive/transfers/__init__.py
airflow/providers/apache/hive/transfers/hive_to_mysql.py
airflow/providers/apache/hive/transfers/hive_to_samba.py
airflow/providers/apache/hive/transfers/mssql_to_hive.py
airflow/providers/apache/hive/transfers/mysql_to_hive.py
airflow/providers/apache/hive/transfers/s3_to_hive.py
airflow/providers/apache/hive/transfers/vertica_to_hive.py
apache_airflow_providers_apache_hive-9.2.3.dist-info/entry_points.txt
apache_airflow_providers_apache_hive-9.2.3.dist-info/licenses/LICENSE
apache_airflow_providers_apache_hive-9.2.3.dist-info/licenses/NOTICE
apache_airflow_providers_apache_hive-9.2.3.dist-info/WHEEL
apache_airflow_providers_apache_hive-9.2.3.dist-info/METADATA
apache_airflow_providers_apache_hive-9.2.3.dist-info/RECORD
