Metadata-Version: 2.4
Name: apache-airflow-providers-apache-hive
Version: 9.2.3
Summary: Provider package apache-airflow-providers-apache-hive for Apache Airflow
Keywords: airflow-provider,apache.hive,airflow,integration
Author-email: Apache Software Foundation <dev@airflow.apache.org>
Maintainer-email: Apache Software Foundation <dev@airflow.apache.org>
Requires-Python: >=3.10
License-Expression: Apache-2.0
Classifier: Development Status :: 5 - Production/Stable
Classifier: Environment :: Console
Classifier: Environment :: Web Environment
Classifier: Intended Audience :: Developers
Classifier: Intended Audience :: System Administrators
Classifier: Framework :: Apache Airflow
Classifier: Framework :: Apache Airflow :: Provider
Classifier: Programming Language :: Python :: 3.10
Classifier: Programming Language :: Python :: 3.11
Classifier: Programming Language :: Python :: 3.12
Classifier: Programming Language :: Python :: 3.13
Classifier: Topic :: System :: Monitoring
License-File: LICENSE
License-File: NOTICE
Requires-Dist: apache-airflow>=2.11.0
Requires-Dist: apache-airflow-providers-common-compat>=1.12.0
Requires-Dist: apache-airflow-providers-common-sql>=1.26.0
Requires-Dist: hmsclient>=0.1.0
Requires-Dist: pandas>=2.1.2; python_version <"3.13"
Requires-Dist: pandas>=2.2.3; python_version >="3.13"
Requires-Dist: pyhive[hive-pure-sasl]>=0.7.0
Requires-Dist: jmespath>=0.7.0
Requires-Dist: apache-airflow-providers-amazon ; extra == "amazon"
Requires-Dist: winkerberos>=0.7.0 ; extra == "gssapi" and ( sys_platform == "win32")
Requires-Dist: kerberos>=1.3.0 ; extra == "gssapi" and ( sys_platform != "win32")
Requires-Dist: apache-airflow-providers-microsoft-mssql ; extra == "microsoft-mssql"
Requires-Dist: apache-airflow-providers-mysql ; extra == "mysql"
Requires-Dist: apache-airflow-providers-presto ; extra == "presto"
Requires-Dist: apache-airflow-providers-samba ; extra == "samba"
Requires-Dist: apache-airflow-providers-vertica ; extra == "vertica"
Project-URL: Bug Tracker, https://github.com/apache/airflow/issues
Project-URL: Changelog, https://airflow.apache.org/docs/apache-airflow-providers-apache-hive/9.2.3/changelog.html
Project-URL: Documentation, https://airflow.apache.org/docs/apache-airflow-providers-apache-hive/9.2.3
Project-URL: Mastodon, https://fosstodon.org/@airflow
Project-URL: Slack Chat, https://s.apache.org/airflow-slack
Project-URL: Source Code, https://github.com/apache/airflow
Project-URL: YouTube, https://www.youtube.com/channel/UCSXwxpWZQ7XZ1WL3wqevChA/
Provides-Extra: amazon
Provides-Extra: gssapi
Provides-Extra: microsoft-mssql
Provides-Extra: mysql
Provides-Extra: presto
Provides-Extra: samba
Provides-Extra: vertica
